POVME/POVME2_GUI.py
POVME/POVME3.py
POVME/POVME_pocket_id.py
POVME/__init__.py
POVME/examples/analysis_workflow_example/runWorkflow.sh
POVME/examples/analysis_workflow_example/1-trajectories/1UYF_every50ns_aligned.pdb
POVME/examples/analysis_workflow_example/1-trajectories/1UYI_every50ns_aligned.pdb
POVME/examples/analysis_workflow_example/1-trajectories/1UYL_every50ns_aligned.pdb
POVME/examples/analysis_workflow_example/1-trajectories/3D0B_every50ns_aligned.pdb
POVME/examples/analysis_workflow_example/1-trajectories/4R3M_every50ns_aligned.pdb
POVME/examples/analysis_workflow_example/2-POVME_analysis/makeRunAllScript.py
POVME/examples/analysis_workflow_example/2-POVME_analysis/povme_1UYF_every50ns_input.ini
POVME/examples/analysis_workflow_example/2-POVME_analysis/povme_1UYI_every50ns_input.ini
POVME/examples/analysis_workflow_example/2-POVME_analysis/povme_1UYL_every50ns_input.ini
POVME/examples/analysis_workflow_example/2-POVME_analysis/povme_3D0B_every50ns_input.ini
POVME/examples/analysis_workflow_example/2-POVME_analysis/povme_4R3M_every50ns_input.ini
POVME/examples/analysis_workflow_example/2-POVME_analysis/runAll.sh
POVME/examples/analysis_workflow_example/3-post_analysis/analyzeClusterMembershipInGroups.py
POVME/examples/analysis_workflow_example/3-post_analysis/analyzeClusterMembershipInGroups_HSP90.py
POVME/examples/analysis_workflow_example/3-post_analysis/makeRunAll.py
POVME/examples/basic_example/4NSS.pdb
POVME/examples/basic_example/sample_POVME_input.for_windows.ini
POVME/examples/basic_example/sample_input.ini
POVME/examples/ligand_example/1BYQ_every250.pdb
POVME/examples/ligand_example/sample_POVME_input.ini
POVME/packages/__init__.py
POVME/packages/binana/__init__.py
POVME/packages/binana/binana.py
POVME/packages/binana/peel.py
POVME/packages/clustering/binding_site_overlap.py
POVME/packages/clustering/binding_site_overlap_no_color.py
POVME/packages/clustering/cluster.py
POVME/packages/clustering/pocketPointsPca.py
POVME-3.0.35.dist-info/DESCRIPTION.rst
POVME-3.0.35.dist-info/METADATA
POVME-3.0.35.dist-info/RECORD
POVME-3.0.35.dist-info/WHEEL
POVME-3.0.35.dist-info/metadata.json
POVME-3.0.35.dist-info/top_level.txt
