Metadata-Version: 2.0
Name: POVME
Version: 3.0.35
Summary: POVME (Pocket VOlume MEasurer) is a Python package for extracting actionable information from ensembles of protein structures for use in drug design.
Home-page: https://github.com/POVME/POVME
Author: Jeff Wagner
Author-email: j5wagner@ucsd.edu
License: UNKNOWN
Download-URL: https://github.com/POVME/POVME/tarball/2.0
Keywords: protein folding,protein,pocket volume measurer,computational protein folding,protein structures,drug design
Platform: UNKNOWN
Classifier: Development Status :: 4 - Beta
Classifier: Environment :: Console
Classifier: Intended Audience :: Science/Research
Classifier: License :: OSI Approved :: MIT License
Classifier: Natural Language :: English
Classifier: Programming Language :: Python :: 2.7
Classifier: Topic :: Scientific/Engineering :: Bio-Informatics
Classifier: Topic :: Scientific/Engineering :: Chemistry
Requires-Dist: matplotlib
Requires-Dist: networkx
Requires-Dist: numpy
Requires-Dist: scipy
